{
  "name": "health-check-ai-mcp",
  "title": "Health Check Ai Mcp",
  "description": "Health Check Ai tools for AI agents. Capabilities: check url, check multiple, check ssl. Built by MEOK AI Labs.",
  "version": "1.0.6",
  "homepage": "https://meok.ai",
  "license": "MIT",
  "transport": {
    "type": "stdio"
  },
  "tools": [
    {
      "name": "check_endpoint"
    },
    {
      "name": "batch_check"
    },
    {
      "name": "get_uptime_report"
    },
    {
      "name": "configure_monitor"
    }
  ]
}
